README.md
setup.py
cjourney/__init__.py
cjourney/cjourney.py
cjourney.egg-info/PKG-INFO
cjourney.egg-info/SOURCES.txt
cjourney.egg-info/dependency_links.txt
cjourney.egg-info/requires.txt
cjourney.egg-info/top_level.txt