Metadata-Version: 2.1
Name: cjourney
Version: 0.0.1
Summary: cjourney is a moudle to analyse customer journey in app
Home-page: https://github.com/renyumm
Author: ryanren
Author-email: strrenyumm@gmail.com
License: UNKNOWN
Platform: UNKNOWN
Classifier: Programming Language :: Python :: 3
Classifier: License :: OSI Approved :: MIT License
Classifier: Operating System :: OS Independent
